alyf/__init__.py
alyf/__main__.py
alyf/upload.py
aliyunfile_cli-1.0.3.dist-info/LICENSE
aliyunfile_cli-1.0.3.dist-info/METADATA
aliyunfile_cli-1.0.3.dist-info/WHEEL
aliyunfile_cli-1.0.3.dist-info/entry_points.txt
aliyunfile_cli-1.0.3.dist-info/top_level.txt
aliyunfile_cli-1.0.3.dist-info/RECORD
