Metadata-Version: 2.1
Name: aliyunfile-cli
Version: 1.0.3
Summary: A simple cli tool for the sick aliyunfile
Author: Han Yi <hanystudy@gmail.com>
Maintainer: Han Yi <hanystudy@gmail.com>
License: MIT License
License-File: LICENSE
Requires-Dist: requests ==2.32.3
Requires-Dist: tqdm ==4.66.4
Requires-Dist: crcmod ==1.7
